{
  "neoforge:conditions": [
    {
      "type": "neoforge:mod_loaded",
      "modid": "extendedae"
    },
    {
      "type": "neoforge:not",
      "value": {
        "type": "neoforge:mod_loaded",
        "modid": "megacells"
      }
    },
    {
      "type": "neoforge:not",
      "value": {
        "type": "neoforge:mod_loaded",
        "modid": "advanced_ae"
      }
    }
  ],
  "type": "minecraft:crafting_shaped",
  "category": "misc",
  "key": {
    "a": {
      "item": "ae2:quartz_vibrant_glass"
    },
    "b": {
      "item": "extendedae:concurrent_processor"
    },
    "c": {
      "item": "ae2:sky_dust"
    },
    "d": {
      "item": "enderdrives:ender_storage_component_256k"
    },
    "e": {
      "item": "extendedae:entro_block"
    },
    "f": {
      "item": "minecraft:ender_chest"
    }
  },
  "pattern": [
    "aba",
    "cdc",
    "efe"
  ],
  "result": {
    "count": 1,
    "id": "enderdrives:ender_disk_256k"
  }
}